cdiscbuilder/__init__.py
cdiscbuilder/cli.py
cdiscbuilder/adam/__init__.py
cdiscbuilder/adam/schema.yaml
cdiscbuilder/adam/adam_derivation/__init__.py
cdiscbuilder/adam/adam_derivation/engine.py
cdiscbuilder/adam/adam_derivation/derivations/__init__.py
cdiscbuilder/adam/adam_derivation/derivations/base.py
cdiscbuilder/adam/adam_derivation/derivations/function_derivation.py
cdiscbuilder/adam/adam_derivation/derivations/sql_derivation.py
cdiscbuilder/adam/adam_derivation/functions/__init__.py
cdiscbuilder/adam/adam_derivation/functions/get_bmi.py
cdiscbuilder/adam/adam_derivation/loaders/__init__.py
cdiscbuilder/adam/adam_derivation/loaders/sdtm_loader.py
cdiscbuilder/adam/adam_derivation/utils/__init__.py
cdiscbuilder/adam/adam_derivation/utils/logger.py
cdiscbuilder/adam/adam_spec/__init__.py
cdiscbuilder/adam/adam_spec/adam_spec.py
cdiscbuilder/adam/adam_spec/merge_yaml.py
cdiscbuilder/adam/adam_spec/schema_validator.py
cdiscbuilder/adam/adam_spec/tests/__init__.py
cdiscbuilder/adam/adam_spec/tests/test_adam_spec.py
cdiscbuilder/adam/adam_spec/tests/test_merge_yaml.py
cdiscbuilder/adam/adam_spec/tests/test_schema_validator.py
cdiscbuilder/adam/adam_spec/tests/data/scenarios/schema.yaml
cdiscbuilder/adam/adam_spec/tests/data/scenarios/organization/adsl_common.yaml
cdiscbuilder/adam/adam_spec/tests/data/scenarios/project/adsl_project.yaml
cdiscbuilder/adam/adam_spec/tests/data/scenarios/study1/adam_study1.yaml
cdiscbuilder/adam/adam_spec/tests/data/scenarios/study1/adsl_study1.yaml
cdiscbuilder/adam/adam_spec/tests/data/scenarios/study1/final_adsl_study1.yaml
cdiscbuilder/adam/adam_spec/tests/data/scenarios/study2/adam_study2.yaml
cdiscbuilder/adam/adam_spec/tests/data/scenarios/study2/adsl_study2.yaml
cdiscbuilder/adam/adam_spec/tests/data/scenarios/study2/final_adsl_study2.yaml
cdiscbuilder/adam/adam_validation/__init__.py
cdiscbuilder/adam/adam_validation/data_validator.py
cdiscbuilder/sdtm/__init__.py
cdiscbuilder/sdtm/odm_parser.py
cdiscbuilder/sdtm/sdtm.py
cdiscbuilder-1.1.7.dist-info/licenses/LICENSE
cdiscbuilder-1.1.7.dist-info/METADATA
cdiscbuilder-1.1.7.dist-info/WHEEL
cdiscbuilder-1.1.7.dist-info/entry_points.txt
cdiscbuilder-1.1.7.dist-info/top_level.txt
cdiscbuilder-1.1.7.dist-info/RECORD
