Metadata-Version: 2.4
Name: cdiscbuilder
Version: 1.1.7
Summary: A package to convert ODM XML to SDTM/ADaM Datasets
Author-email: Ming-Chun Chen <hellomingchun@gmail.com>
Requires-Python: >=3.8
License-File: LICENSE
Requires-Dist: pandas
Requires-Dist: pyyaml
Requires-Dist: polars>=0.20.0
Requires-Dist: reactable>=0.1.6
Dynamic: license-file
